arrangio/__init__.py
arrangio/__init__.pyi
arrangio/__main__.py
arrangio/_parser_.py
arrangio/_parser_.pyi
arrangio/_utils_.py
arrangio/_utils_.pyi
arrangio/py.typed
arrangio-0.5.1.dist-info/METADATA
arrangio-0.5.1.dist-info/WHEEL
arrangio-0.5.1.dist-info/entry_points.txt
arrangio-0.5.1.dist-info/licenses/LICENSE
arrangio-0.5.1.dist-info/RECORD
