Metadata-Version: 2.3
Name: arrangio
Version: 0.5.1
Summary: Arranges a set of songs in groups with similar total play time.
Project-URL: Documentation, http://electric-mass.github.io/arrangio
Project-URL: Homepage, https://github.com/electric-mass/arrangio
Project-URL: Source, https://github.com/electric-mass/arrangio
Author: Frederico Martins
License: MIT
License-File: LICENSE
Keywords: grouping,songs
Classifier: Development Status :: 4 - Beta
Classifier: Environment :: Console
Classifier: Intended Audience :: End Users/Desktop
Classifier: License :: OSI Approved :: MIT License
Classifier: Operating System :: OS Independent
Classifier: Programming Language :: Python :: 3
Classifier: Programming Language :: Python :: 3 :: Only
Classifier: Programming Language :: Python :: 3.8
Classifier: Programming Language :: Python :: 3.9
Classifier: Programming Language :: Python :: 3.10
Classifier: Programming Language :: Python :: 3.11
Classifier: Programming Language :: Python :: 3.12
Classifier: Topic :: Utilities
Classifier: Typing :: Typed
Requires-Python: <4,>=3.8
Provides-Extra: dev
Requires-Dist: autopep8>=1.6.0; extra == 'dev'
Requires-Dist: build>=0.8.0; extra == 'dev'
Requires-Dist: coverage[toml]>=6.4.1; extra == 'dev'
Requires-Dist: mypy>=0.950; extra == 'dev'
Requires-Dist: pdoc3>=0.10.0; extra == 'dev'
Requires-Dist: pylint>=2.13.9; extra == 'dev'
Requires-Dist: pytest-cov>=3.0.0; extra == 'dev'
Requires-Dist: pytest-custom-exit-code>=0.3.0; extra == 'dev'
Requires-Dist: pytest-mock>=3.8.2; extra == 'dev'
Requires-Dist: pytest>=7.1.2; extra == 'dev'
Requires-Dist: ruff>=0.0.282; extra == 'dev'
Requires-Dist: twine>=4.0.0; extra == 'dev'
Requires-Dist: vermin>=1.4.0; extra == 'dev'
